{
 "based_on": "",
 "chart_name": "Orphans by country",
 "chart_type": "Group By",
 "color": "#29CD42",
 "creation": "2023-07-12 22:55:19.371498",
 "docstatus": 0,
 "doctype": "Dashboard Chart",
 "document_type": "Orphan",
 "dynamic_filters_json": "[]",
 "filters_json": "[]",
 "group_by_based_on": "nationality_orphan",
 "group_by_type": "Count",
 "idx": 0,
 "is_public": 1,
 "is_standard": 1,
 "last_synced_on": "2023-06-17 16:45:42.745065",
 "modified": "2023-07-12 22:55:19.371498",
 "modified_by": "Administrator",
 "module": "Social Helpers",
 "name": "Orphans by country",
 "number_of_groups": 0,
 "owner": "Administrator",
 "parent_document_type": "",
 "roles": [],
 "source": "",
 "time_interval": "Yearly",
 "timeseries": 0,
 "timespan": "Last Year",
 "type": "Donut",
 "use_report_chart": 0,
 "value_based_on": "",
 "y_axis": []
}